push_api_clientpy/__init__.py
push_api_clientpy/document.py
push_api_clientpy/documentbuilder.py
push_api_clientpy/platformclient.py
push_api_clientpy/securityidentitybuilder.py
push_api_clientpy/source.py
coveo_push_api_client.py-1.1.2.dist-info/AUTHORS.rst
coveo_push_api_client.py-1.1.2.dist-info/LICENSE.txt
coveo_push_api_client.py-1.1.2.dist-info/METADATA
coveo_push_api_client.py-1.1.2.dist-info/WHEEL
coveo_push_api_client.py-1.1.2.dist-info/top_level.txt
coveo_push_api_client.py-1.1.2.dist-info/RECORD
