Metadata-Version: 2.1
Name: coveo-push-api-client.py
Version: 1.1.2
Summary: Python Push API Client
Home-page: https://github.com/coveo/push-api-client.py
Author: Olivier Lamothe
Author-email: olamothe@coveo.com
License: MIT
Project-URL: Homepage, https://github.com/coveo/push-api-client.py
Platform: any
Classifier: Development Status :: 4 - Beta
Classifier: Programming Language :: Python
Requires-Python: >=3.9
License-File: LICENSE.txt
License-File: AUTHORS.rst
Requires-Dist: python-dateutil
Requires-Dist: requests
Requires-Dist: importlib-metadata ; python_version < "3.8"
Provides-Extra: testing
Requires-Dist: setuptools ; extra == 'testing'
Requires-Dist: pytest ; extra == 'testing'
Requires-Dist: pytest-cov ; extra == 'testing'
Requires-Dist: requests-mock ; extra == 'testing'
